intent/__init__.py
intent/cli.py
intent/config.py
intent/fs.py
intent/pyproject_reader.py
intent/render_ci.py
intent/render_just.py
intent/versioning.py
intent_cli-0.1.0.dist-info/METADATA
intent_cli-0.1.0.dist-info/WHEEL
intent_cli-0.1.0.dist-info/entry_points.txt
intent_cli-0.1.0.dist-info/top_level.txt
intent_cli-0.1.0.dist-info/RECORD
