Metadata-Version: 2.4
Name: intent-cli
Version: 0.1.0
Summary: Safety-first tool to generate tool-owned project files from intent.toml
Author: sankarebarri
License: MIT
Project-URL: Homepage, https://github.com/sankarebarri/intent
Project-URL: Repository, https://github.com/sankarebarri/intent
Project-URL: Issues, https://github.com/sankarebarri/intent/issues
Keywords: ci,github-actions,justfile,just,automation,scaffolding,generator,devtools,tooling,configuration
Classifier: Development Status :: 3 - Alpha
Classifier: Environment :: Console
Classifier: Intended Audience :: Developers
Classifier: License :: OSI Approved :: MIT License
Classifier: Operating System :: OS Independent
Classifier: Programming Language :: Python :: 3
Classifier: Programming Language :: Python :: 3.12
Classifier: Topic :: Software Development :: Build Tools
Classifier: Topic :: Software Development :: Quality Assurance
Classifier: Topic :: Utilities
Requires-Python: >=3.12
Requires-Dist: typer>=0.9
Provides-Extra: dev
Requires-Dist: pytest>=8; extra == "dev"
Requires-Dist: ruff>=0.4; extra == "dev"
Requires-Dist: build>=1.0; extra == "dev"
Requires-Dist: twine>=5.0; extra == "dev"
